hellototi.py
pypipackaging.py
PyPipackaging-0.0.8.dist-info/LICENSE.txt
PyPipackaging-0.0.8.dist-info/METADATA
PyPipackaging-0.0.8.dist-info/WHEEL
PyPipackaging-0.0.8.dist-info/top_level.txt
PyPipackaging-0.0.8.dist-info/RECORD
