Metadata-Version: 2.1
Name: PyPipackaging
Version: 0.0.8
Summary: Say Hello
Home-page: https://github.com/Totilarson/CorePy
Author: Toti Larson
Author-email: totlarson@gmail.com
License: LICENSE.txt
Platform: UNKNOWN
Classifier: License :: OSI Approved :: MIT License
Classifier: Programming Language :: Python :: 3
Classifier: Programming Language :: Python :: 3.7
License-File: LICENSE.txt
